indian_name_maker/__init__.py
indian_name_maker/generator.py
indian_name_maker/main.py
indian_name_maker/name_generator.py
indian_name_maker/data/first_names.csv
indian_name_maker/data/last_names.csv
indian_name_maker-0.1.4.dist-info/LICENSE
indian_name_maker-0.1.4.dist-info/METADATA
indian_name_maker-0.1.4.dist-info/WHEEL
indian_name_maker-0.1.4.dist-info/entry_points.txt
indian_name_maker-0.1.4.dist-info/top_level.txt
indian_name_maker-0.1.4.dist-info/RECORD
