Metadata-Version: 2.1
Name: indian-name-maker
Version: 0.1.4
Summary: A Python package to generate Indian names
Author: Ankit Kumar
License: CC BY-NC-SA 4.0
Keywords: indian,names,generator
Classifier: Development Status :: 3 - Alpha
Classifier: Intended Audience :: Developers
Classifier: License :: Other/Proprietary License
Classifier: Operating System :: OS Independent
Requires-Python: >=3.7
License-File: LICENSE
Requires-Dist: pandas>=1.3.0
Requires-Dist: numpy>=1.23.2
Requires-Dist: pytest>=7.0.0
